README.md
README.rst
setup.py
htrc_feature_reader.egg-info/PKG-INFO
htrc_feature_reader.egg-info/SOURCES.txt
htrc_feature_reader.egg-info/dependency_links.txt
htrc_feature_reader.egg-info/entry_points.txt
htrc_feature_reader.egg-info/not-zip-safe
htrc_feature_reader.egg-info/requires.txt
htrc_feature_reader.egg-info/top_level.txt
htrc_features/__init__.py
htrc_features/caching.py
htrc_features/config.py
htrc_features/feature_reader.py
htrc_features/parsers.py
htrc_features/resolvers.py
htrc_features/transformations.py
htrc_features/utils.py