Metadata-Version: 2.1
Name: htrc-feature-reader
Version: 2.0.6
Summary: Library for working with the HTRC Extracted Features dataset
Home-page: https://github.com/organisciak/htrc-feature-reader
Author: Peter Organisciak
Author-email: organisciak@gmail.com
License: NCSA
Keywords: hathitrust text-mining text-analysis features
Platform: UNKNOWN
Classifier: Development Status :: 5 - Production/Stable
Classifier: License :: OSI Approved :: University of Illinois/NCSA Open Source License
Classifier: Programming Language :: Python :: 3.6
Classifier: Programming Language :: Python :: 3.7
Classifier: Natural Language :: English
